vdntru/__init__.py
vdntru/decryption.py
vdntru/encryption.py
vdntru-1.0.0.dist-info/METADATA
vdntru-1.0.0.dist-info/WHEEL
vdntru-1.0.0.dist-info/top_level.txt
vdntru-1.0.0.dist-info/RECORD
